odoo/addons/monitoring_prometheus/README.rst
odoo/addons/monitoring_prometheus/__init__.py
odoo/addons/monitoring_prometheus/__manifest__.py
odoo/addons/monitoring_prometheus/controllers/__init__.py
odoo/addons/monitoring_prometheus/controllers/prometheus_metrics.py
odoo/addons/monitoring_prometheus/models/__init__.py
odoo/addons/monitoring_prometheus/models/ir_http.py
odoo12_addon_monitoring_prometheus-12.0.1.0.0.dist-info/METADATA
odoo12_addon_monitoring_prometheus-12.0.1.0.0.dist-info/WHEEL
odoo12_addon_monitoring_prometheus-12.0.1.0.0.dist-info/top_level.txt
odoo12_addon_monitoring_prometheus-12.0.1.0.0.dist-info/RECORD
